This XML file does not appear to have any style information associated with it. The document tree is shown below.
<VAST xmlns:xsi="http://www.w3.org/2001/XMLSchema-instance" version="3.0" xsi:noNamespaceSchemaLocation="vast.xsd">
	<Ad id="1" sequence="1">
		<InLine>
			<AdSystem>
				<![CDATA[ Reviveadservermod.com ]]>
			</AdSystem>
			<AdTitle>
				<![CDATA[ ad 2 ]]>
			</AdTitle>
			<Impression>
				<![CDATA[ https://krish.g-mana.net/media/debug/impression?impression=1&adId=1 ]]>
			</Impression>
			<Creatives>
				<Creative>
					<Linear>
						<Duration>
							00:00:10
						</Duration>
						<TrackingEvents>
							<Tracking event="start">
								<![CDATA[ https://jsonplaceholder.typicode.com/todos/1?event=start&adId=1 ]]>
							</Tracking>
							<Tracking event="firstQuartile">
								<![CDATA[ https://jsonplaceholder.typicode.com/todos/1?event=firstquartile&adId=1 ]]>
							</Tracking>
							<Tracking event="midpoint">
								<![CDATA[ https://jsonplaceholder.typicode.com/todos/1?event=midpoint&adId=1 ]]>
							</Tracking>
							<Tracking event="thirdQuartile">
								<![CDATA[ https://jsonplaceholder.typicode.com/todos/1?event=thirdquartile&adId=1 ]]>
							</Tracking>
							<Tracking event="complete">
								<![CDATA[ https://jsonplaceholder.typicode.com/todos/1?event=complete&adId=1 ]]>
							</Tracking>
							<Tracking event="pause">
								<![CDATA[ https://jsonplaceholder.typicode.com/todos/1?script=rmvideoAds:rmvastEvent&bannerid=10&zoneid=4&event=pause ]]>
							</Tracking>
							<Tracking event="mute">
								<![CDATA[ https://jsonplaceholder.typicode.com/todos/1?script=rmvideoAds:rmvastEvent&bannerid=10&zoneid=4&event=mute ]]>
							</Tracking>
							<Tracking event="fullscreen">
								<![CDATA[ https://jsonplaceholder.typicode.com/todos/1?script=rmvideoAds:rmvastEvent&bannerid=10&zoneid=4&event=fullscreen ]]>
							</Tracking>
							<Tracking event="unmute">
								<![CDATA[ https://jsonplaceholder.typicode.com/todos/1?script=rmvideoAds:rmvastEvent&bannerid=10&zoneid=4&event=unmute ]]>
							</Tracking>
							<Tracking event="closeLinear">
								<![CDATA[ https://krish.g-mana.net/media/debug/impression/fc.php?script=rmvideoAds:rmvastEvent&bannerid=10&zoneid=4&event=closeLinear ]]>
							</Tracking>
							<Tracking event="acceptInvitationLinear">
								<![CDATA[ https://krish.g-mana.net/media/debug/impression/fc.php?script=rmvideoAds:rmvastEvent&bannerid=10&zoneid=4&event=acceptInvitationLinear ]]>
							</Tracking>
							<Tracking event="skip">
								<![CDATA[ https://krish.g-mana.net/media/debug/impression/fc.php?script=rmvideoAds:rmvastEvent&bannerid=10&zoneid=4&event=skip ]]>
							</Tracking>
							<Tracking event="progress">
								<![CDATA[ https://krish.g-mana.net/media/debug/impression/fc.php?script=rmvideoAds:rmvastEvent&bannerid=10&zoneid=4&event=progress ]]>
							</Tracking>
							<Tracking event="exitFullscreen">
								<![CDATA[ https://krish.g-mana.net/media/debug/impression/fc.php?script=rmvideoAds:rmvastEvent&bannerid=10&zoneid=4&event=exitfullscreen ]]>
							</Tracking>
							<Tracking event="rewind">
								<![CDATA[ https://krish.g-mana.et/media/debug/impression/fc.php?script=rmvideoAds:rmvastEvent&bannerid=10&zoneid=4&event=rewind ]]>
							</Tracking>
							<Tracking event="resume">
								<![CDATA[ https://krish.g-mana.net/media/debug/impression/fc.php?script=rmvideoAds:rmvastEvent&bannerid=10&zoneid=4&event=resume ]]>
							</Tracking>
						</TrackingEvents>
						<MediaFiles>
							<MediaFile delivery="progressive" bitrate="128000" width="1280" height="720" type="video/mp4" scalable="true" maintainAspectRatio="true">
								<![CDATA[ https://cdn.g-mana.online/media/assets/IZ%20juice%20it's%20simply%20amazing%20!%2010%20sec%20Ad.mp4 ]]>
							</MediaFile>
						</MediaFiles>
					</Linear>
				</Creative>
			</Creatives>
		</InLine>
	</Ad>
</VAST>
